aiq_platform_api/__init__.py
aiq_platform_api/assessment_use_cases.py
aiq_platform_api/asset_use_cases.py
aiq_platform_api/core/__init__.py
aiq_platform_api/core/assessments.py
aiq_platform_api/core/assets.py
aiq_platform_api/core/async_utils.py
aiq_platform_api/core/client.py
aiq_platform_api/core/connectors.py
aiq_platform_api/core/constants.py
aiq_platform_api/core/files.py
aiq_platform_api/core/logger.py
aiq_platform_api/core/mitigations.py
aiq_platform_api/core/results.py
aiq_platform_api/core/scenarios.py
aiq_platform_api/core/tags.py
aiq_platform_api/core/testing.py
aiq_platform_api/env.py
aiq_platform_api/file_use_cases.py
aiq_platform_api/integration_use_cases.py
aiq_platform_api/phase_log_use_cases.py
aiq_platform_api/phase_results_use_cases.py
aiq_platform_api/result_use_cases.py
aiq_platform_api/scenario_use_cases.py
aiq_platform_api/tag_use_cases.py
aiq_platform_api/unified_mitigation_use_cases.py
aiq_platform_api-1.0.33.dist-info/METADATA
aiq_platform_api-1.0.33.dist-info/WHEEL
aiq_platform_api-1.0.33.dist-info/licenses/LICENSE
aiq_platform_api-1.0.33.dist-info/RECORD
