Metadata-Version: 2.4
Name: aiq-platform-api
Version: 1.0.33
Summary: Utility functions for AttackIQ Platform API usage
License: MIT
License-File: LICENSE
Author: Rajesh Sharma
Author-email: rajesh.sharma@attackiq.com
Requires-Python: >=3.11,<3.13
Classifier: License :: OSI Approved :: MIT License
Classifier: Programming Language :: Python :: 3
Classifier: Programming Language :: Python :: 3.11
Classifier: Programming Language :: Python :: 3.12
Requires-Dist: httpx (>=0.27,<1.0)
Requires-Dist: ipython (>=7.34.0,<9.0.0)
Requires-Dist: python-dotenv (>=1.0.1,<2.0.0)
Requires-Dist: pyzipper (>=0.3.6,<0.4.0)
Requires-Dist: tenacity (>=8.2.3)
